{
  "entityId": 157,
  "entityUUID": "34637c7b-abb7-494b-ae8f-d9e397584001",
  "type": 94,
  "x": 223.5,
  "y": 53,
  "z": -165.5,
  "yaw": 33,
  "pitch": 0,
  "headPitch": 2,
  "velocityX": 0,
  "velocityY": 0,
  "velocityZ": 0,
  "metadata": [
    {
      "key": 0,
      "type": 0,
      "value": 0
    },
    {
      "key": 1,
      "type": 1,
      "value": 300
    },
    {
      "key": 2,
      "type": 3,
      "value": ""
    },
    {
      "key": 3,
      "type": 6,
      "value": false
    },
    {
      "key": 4,
      "type": 6,
      "value": false
    },
    {
      "key": 5,
      "type": 0,
      "value": 0
    },
    {
      "key": 6,
      "type": 2,
      "value": 10
    },
    {
      "key": 7,
      "type": 1,
      "value": 0
    },
    {
      "key": 8,
      "type": 6,
      "value": false
    },
    {
      "key": 9,
      "type": 1,
      "value": 0
    },
    {
      "key": 10,
      "type": 0,
      "value": 0
    }
  ]
}